<profile>

<RTLDesignHierarchy>
<TopModule>
<ModuleName>q5_cyclic_partition</ModuleName>
</TopModule>
</RTLDesignHierarchy>

<ModuleInformation>
<Module>
<Name>q5_cyclic_partition</Name>
<Loops>
<VITIS_LOOP_117_1></VITIS_LOOP_117_1>
</Loops>
<PerformanceEstimates>
<SummaryOfTimingAnalysis>
<TargetClockPeriod>25.00</TargetClockPeriod>
<ClockUncertainty>6.75</ClockUncertainty>
<EstimatedClockPeriod>5.448</EstimatedClockPeriod>
</SummaryOfTimingAnalysis>
<SummaryOfOverallLatency>
<Best-caseLatency>18</Best-caseLatency>
<Average-caseLatency>18</Average-caseLatency>
<Worst-caseLatency>18</Worst-caseLatency>
<Best-caseRealTimeLatency>0.450 us</Best-caseRealTimeLatency>
<Average-caseRealTimeLatency>0.450 us</Average-caseRealTimeLatency>
<Worst-caseRealTimeLatency>0.450 us</Worst-caseRealTimeLatency>
<PipelineInitiationInterval>16</PipelineInitiationInterval>
<PipelineType>loop auto-rewind (delay=0 clock cycles(s))</PipelineType>
</SummaryOfOverallLatency>
<SummaryOfLoopLatency>
<VITIS_LOOP_117_1>
<Name>VITIS_LOOP_117_1</Name>
<Slack>18.25</Slack>
<TripCount>16</TripCount>
<Latency>16</Latency>
<AbsoluteTimeLatency>0.400 us</AbsoluteTimeLatency>
<PipelineII>1</PipelineII>
<PipelineDepth>2</PipelineDepth>
<PipelineType>yes</PipelineType>
<InstanceList>
</InstanceList>
</VITIS_LOOP_117_1>
</SummaryOfLoopLatency>
<SummaryOfViolations>
<IssueType>-</IssueType>
<ViolationType>-</ViolationType>
<SourceLocation>q5_kernel.cpp:102</SourceLocation>
<SummaryOfLoopViolations>
<VITIS_LOOP_117_1>
<Name>VITIS_LOOP_117_1</Name>
<IssueType>-</IssueType>
<ViolationType>-</ViolationType>
<SourceLocation>q5_kernel.cpp:117</SourceLocation>
</VITIS_LOOP_117_1>
</SummaryOfLoopViolations>
</SummaryOfViolations>
</PerformanceEstimates>
<AreaEstimates>
<Resources>
<BRAM_18K>0</BRAM_18K>
<AVAIL_BRAM>5376</AVAIL_BRAM>
<UTIL_BRAM>0</UTIL_BRAM>
<DSP>24</DSP>
<AVAIL_DSP>12288</AVAIL_DSP>
<UTIL_DSP>~0</UTIL_DSP>
<FF>51</FF>
<AVAIL_FF>3456000</AVAIL_FF>
<UTIL_FF>~0</UTIL_FF>
<LUT>566</LUT>
<AVAIL_LUT>1728000</AVAIL_LUT>
<UTIL_LUT>~0</UTIL_LUT>
<URAM>0</URAM>
<AVAIL_URAM>1280</AVAIL_URAM>
<UTIL_URAM>0</UTIL_URAM>
</Resources>
</AreaEstimates>
<InterfaceSummary>
<RtlPorts>
<name>s_axi_control_AWVALID</name>
<Object>control</Object>
<Type>return void</Type>
<IOProtocol>s_axi</IOProtocol>
<Dir>in</Dir>
<Bits>1</Bits>
<Attribute>unknown</Attribute>
<CType>unknown</CType>
<HasCtrl>1</HasCtrl>
</RtlPorts>
<RtlPorts>
<name>s_axi_control_AWREADY</name>
<Object>control</Object>
<Type>return void</Type>
<IOProtocol>s_axi</IOProtocol>
<Dir>out</Dir>
<Bits>1</Bits>
<Attribute>unknown</Attribute>
<CType>unknown</CType>
<HasCtrl>1</HasCtrl>
</RtlPorts>
<RtlPorts>
<name>s_axi_control_AWADDR</name>
<Object>control</Object>
<Type>return void</Type>
<IOProtocol>s_axi</IOProtocol>
<Dir>in</Dir>
<Bits>4</Bits>
<Attribute>unknown</Attribute>
<CType>unknown</CType>
<HasCtrl>1</HasCtrl>
</RtlPorts>
<RtlPorts>
<name>s_axi_control_WVALID</name>
<Object>control</Object>
<Type>return void</Type>
<IOProtocol>s_axi</IOProtocol>
<Dir>in</Dir>
<Bits>1</Bits>
<Attribute>unknown</Attribute>
<CType>unknown</CType>
<HasCtrl>1</HasCtrl>
</RtlPorts>
<RtlPorts>
<name>s_axi_control_WREADY</name>
<Object>control</Object>
<Type>return void</Type>
<IOProtocol>s_axi</IOProtocol>
<Dir>out</Dir>
<Bits>1</Bits>
<Attribute>unknown</Attribute>
<CType>unknown</CType>
<HasCtrl>1</HasCtrl>
</RtlPorts>
<RtlPorts>
<name>s_axi_control_WDATA</name>
<Object>control</Object>
<Type>return void</Type>
<IOProtocol>s_axi</IOProtocol>
<Dir>in</Dir>
<Bits>32</Bits>
<Attribute>unknown</Attribute>
<CType>unknown</CType>
<HasCtrl>1</HasCtrl>
</RtlPorts>
<RtlPorts>
<name>s_axi_control_WSTRB</name>
<Object>control</Object>
<Type>return void</Type>
<IOProtocol>s_axi</IOProtocol>
<Dir>in</Dir>
<Bits>4</Bits>
<Attribute>unknown</Attribute>
<CType>unknown</CType>
<HasCtrl>1</HasCtrl>
</RtlPorts>
<RtlPorts>
<name>s_axi_control_ARVALID</name>
<Object>control</Object>
<Type>return void</Type>
<IOProtocol>s_axi</IOProtocol>
<Dir>in</Dir>
<Bits>1</Bits>
<Attribute>unknown</Attribute>
<CType>unknown</CType>
<HasCtrl>1</HasCtrl>
</RtlPorts>
<RtlPorts>
<name>s_axi_control_ARREADY</name>
<Object>control</Object>
<Type>return void</Type>
<IOProtocol>s_axi</IOProtocol>
<Dir>out</Dir>
<Bits>1</Bits>
<Attribute>unknown</Attribute>
<CType>unknown</CType>
<HasCtrl>1</HasCtrl>
</RtlPorts>
<RtlPorts>
<name>s_axi_control_ARADDR</name>
<Object>control</Object>
<Type>return void</Type>
<IOProtocol>s_axi</IOProtocol>
<Dir>in</Dir>
<Bits>4</Bits>
<Attribute>unknown</Attribute>
<CType>unknown</CType>
<HasCtrl>1</HasCtrl>
</RtlPorts>
<RtlPorts>
<name>s_axi_control_RVALID</name>
<Object>control</Object>
<Type>return void</Type>
<IOProtocol>s_axi</IOProtocol>
<Dir>out</Dir>
<Bits>1</Bits>
<Attribute>unknown</Attribute>
<CType>unknown</CType>
<HasCtrl>1</HasCtrl>
</RtlPorts>
<RtlPorts>
<name>s_axi_control_RREADY</name>
<Object>control</Object>
<Type>return void</Type>
<IOProtocol>s_axi</IOProtocol>
<Dir>in</Dir>
<Bits>1</Bits>
<Attribute>unknown</Attribute>
<CType>unknown</CType>
<HasCtrl>1</HasCtrl>
</RtlPorts>
<RtlPorts>
<name>s_axi_control_RDATA</name>
<Object>control</Object>
<Type>return void</Type>
<IOProtocol>s_axi</IOProtocol>
<Dir>out</Dir>
<Bits>32</Bits>
<Attribute>unknown</Attribute>
<CType>unknown</CType>
<HasCtrl>1</HasCtrl>
</RtlPorts>
<RtlPorts>
<name>s_axi_control_RRESP</name>
<Object>control</Object>
<Type>return void</Type>
<IOProtocol>s_axi</IOProtocol>
<Dir>out</Dir>
<Bits>2</Bits>
<Attribute>unknown</Attribute>
<CType>unknown</CType>
<HasCtrl>1</HasCtrl>
</RtlPorts>
<RtlPorts>
<name>s_axi_control_BVALID</name>
<Object>control</Object>
<Type>return void</Type>
<IOProtocol>s_axi</IOProtocol>
<Dir>out</Dir>
<Bits>1</Bits>
<Attribute>unknown</Attribute>
<CType>unknown</CType>
<HasCtrl>1</HasCtrl>
</RtlPorts>
<RtlPorts>
<name>s_axi_control_BREADY</name>
<Object>control</Object>
<Type>return void</Type>
<IOProtocol>s_axi</IOProtocol>
<Dir>in</Dir>
<Bits>1</Bits>
<Attribute>unknown</Attribute>
<CType>unknown</CType>
<HasCtrl>1</HasCtrl>
</RtlPorts>
<RtlPorts>
<name>s_axi_control_BRESP</name>
<Object>control</Object>
<Type>return void</Type>
<IOProtocol>s_axi</IOProtocol>
<Dir>out</Dir>
<Bits>2</Bits>
<Attribute>unknown</Attribute>
<CType>unknown</CType>
<HasCtrl>1</HasCtrl>
</RtlPorts>
<RtlPorts>
<name>ap_clk</name>
<Object>q5_cyclic_partition</Object>
<Type>return value</Type>
<Scope></Scope>
<IOProtocol>ap_ctrl_hs</IOProtocol>
<IOConfig></IOConfig>
<Dir>in</Dir>
<Bits>1</Bits>
<Attribute>control</Attribute>
</RtlPorts>
<RtlPorts>
<name>ap_rst_n</name>
<Object>q5_cyclic_partition</Object>
<Type>return value</Type>
<Scope></Scope>
<IOProtocol>ap_ctrl_hs</IOProtocol>
<IOConfig></IOConfig>
<Dir>in</Dir>
<Bits>1</Bits>
<Attribute>control</Attribute>
</RtlPorts>
<RtlPorts>
<name>interrupt</name>
<Object>q5_cyclic_partition</Object>
<Type>return value</Type>
<Scope></Scope>
<IOProtocol>ap_ctrl_hs</IOProtocol>
<IOConfig></IOConfig>
<Dir>out</Dir>
<Bits>1</Bits>
<Attribute>unknown</Attribute>
</RtlPorts>
<RtlPorts>
<name>A_0_address0</name>
<Object>A_0</Object>
<Type>array</Type>
<Scope></Scope>
<IOProtocol>ap_memory</IOProtocol>
<IOConfig></IOConfig>
<Dir>out</Dir>
<Bits>4</Bits>
<Attribute>address</Attribute>
<CType>int</CType>
</RtlPorts>
<RtlPorts>
<name>A_0_ce0</name>
<Object>A_0</Object>
<Type>array</Type>
<Scope></Scope>
<IOProtocol>ap_memory</IOProtocol>
<IOConfig></IOConfig>
<Dir>out</Dir>
<Bits>1</Bits>
<Attribute>control</Attribute>
<CType>int</CType>
</RtlPorts>
<RtlPorts>
<name>A_0_q0</name>
<Object>A_0</Object>
<Type>array</Type>
<Scope></Scope>
<IOProtocol>ap_memory</IOProtocol>
<IOConfig></IOConfig>
<Dir>in</Dir>
<Bits>32</Bits>
<Attribute>data</Attribute>
<CType>int</CType>
</RtlPorts>
<RtlPorts>
<name>A_1_address0</name>
<Object>A_1</Object>
<Type>array</Type>
<Scope></Scope>
<IOProtocol>ap_memory</IOProtocol>
<IOConfig></IOConfig>
<Dir>out</Dir>
<Bits>4</Bits>
<Attribute>address</Attribute>
<CType>int</CType>
</RtlPorts>
<RtlPorts>
<name>A_1_ce0</name>
<Object>A_1</Object>
<Type>array</Type>
<Scope></Scope>
<IOProtocol>ap_memory</IOProtocol>
<IOConfig></IOConfig>
<Dir>out</Dir>
<Bits>1</Bits>
<Attribute>control</Attribute>
<CType>int</CType>
</RtlPorts>
<RtlPorts>
<name>A_1_q0</name>
<Object>A_1</Object>
<Type>array</Type>
<Scope></Scope>
<IOProtocol>ap_memory</IOProtocol>
<IOConfig></IOConfig>
<Dir>in</Dir>
<Bits>32</Bits>
<Attribute>data</Attribute>
<CType>int</CType>
</RtlPorts>
<RtlPorts>
<name>A_2_address0</name>
<Object>A_2</Object>
<Type>array</Type>
<Scope></Scope>
<IOProtocol>ap_memory</IOProtocol>
<IOConfig></IOConfig>
<Dir>out</Dir>
<Bits>4</Bits>
<Attribute>address</Attribute>
<CType>int</CType>
</RtlPorts>
<RtlPorts>
<name>A_2_ce0</name>
<Object>A_2</Object>
<Type>array</Type>
<Scope></Scope>
<IOProtocol>ap_memory</IOProtocol>
<IOConfig></IOConfig>
<Dir>out</Dir>
<Bits>1</Bits>
<Attribute>control</Attribute>
<CType>int</CType>
</RtlPorts>
<RtlPorts>
<name>A_2_q0</name>
<Object>A_2</Object>
<Type>array</Type>
<Scope></Scope>
<IOProtocol>ap_memory</IOProtocol>
<IOConfig></IOConfig>
<Dir>in</Dir>
<Bits>32</Bits>
<Attribute>data</Attribute>
<CType>int</CType>
</RtlPorts>
<RtlPorts>
<name>A_3_address0</name>
<Object>A_3</Object>
<Type>array</Type>
<Scope></Scope>
<IOProtocol>ap_memory</IOProtocol>
<IOConfig></IOConfig>
<Dir>out</Dir>
<Bits>4</Bits>
<Attribute>address</Attribute>
<CType>int</CType>
</RtlPorts>
<RtlPorts>
<name>A_3_ce0</name>
<Object>A_3</Object>
<Type>array</Type>
<Scope></Scope>
<IOProtocol>ap_memory</IOProtocol>
<IOConfig></IOConfig>
<Dir>out</Dir>
<Bits>1</Bits>
<Attribute>control</Attribute>
<CType>int</CType>
</RtlPorts>
<RtlPorts>
<name>A_3_q0</name>
<Object>A_3</Object>
<Type>array</Type>
<Scope></Scope>
<IOProtocol>ap_memory</IOProtocol>
<IOConfig></IOConfig>
<Dir>in</Dir>
<Bits>32</Bits>
<Attribute>data</Attribute>
<CType>int</CType>
</RtlPorts>
<RtlPorts>
<name>B_0_address0</name>
<Object>B_0</Object>
<Type>array</Type>
<Scope></Scope>
<IOProtocol>ap_memory</IOProtocol>
<IOConfig></IOConfig>
<Dir>out</Dir>
<Bits>4</Bits>
<Attribute>address</Attribute>
<CType>int</CType>
</RtlPorts>
<RtlPorts>
<name>B_0_ce0</name>
<Object>B_0</Object>
<Type>array</Type>
<Scope></Scope>
<IOProtocol>ap_memory</IOProtocol>
<IOConfig></IOConfig>
<Dir>out</Dir>
<Bits>1</Bits>
<Attribute>control</Attribute>
<CType>int</CType>
</RtlPorts>
<RtlPorts>
<name>B_0_q0</name>
<Object>B_0</Object>
<Type>array</Type>
<Scope></Scope>
<IOProtocol>ap_memory</IOProtocol>
<IOConfig></IOConfig>
<Dir>in</Dir>
<Bits>32</Bits>
<Attribute>data</Attribute>
<CType>int</CType>
</RtlPorts>
<RtlPorts>
<name>B_1_address0</name>
<Object>B_1</Object>
<Type>array</Type>
<Scope></Scope>
<IOProtocol>ap_memory</IOProtocol>
<IOConfig></IOConfig>
<Dir>out</Dir>
<Bits>4</Bits>
<Attribute>address</Attribute>
<CType>int</CType>
</RtlPorts>
<RtlPorts>
<name>B_1_ce0</name>
<Object>B_1</Object>
<Type>array</Type>
<Scope></Scope>
<IOProtocol>ap_memory</IOProtocol>
<IOConfig></IOConfig>
<Dir>out</Dir>
<Bits>1</Bits>
<Attribute>control</Attribute>
<CType>int</CType>
</RtlPorts>
<RtlPorts>
<name>B_1_q0</name>
<Object>B_1</Object>
<Type>array</Type>
<Scope></Scope>
<IOProtocol>ap_memory</IOProtocol>
<IOConfig></IOConfig>
<Dir>in</Dir>
<Bits>32</Bits>
<Attribute>data</Attribute>
<CType>int</CType>
</RtlPorts>
<RtlPorts>
<name>B_2_address0</name>
<Object>B_2</Object>
<Type>array</Type>
<Scope></Scope>
<IOProtocol>ap_memory</IOProtocol>
<IOConfig></IOConfig>
<Dir>out</Dir>
<Bits>4</Bits>
<Attribute>address</Attribute>
<CType>int</CType>
</RtlPorts>
<RtlPorts>
<name>B_2_ce0</name>
<Object>B_2</Object>
<Type>array</Type>
<Scope></Scope>
<IOProtocol>ap_memory</IOProtocol>
<IOConfig></IOConfig>
<Dir>out</Dir>
<Bits>1</Bits>
<Attribute>control</Attribute>
<CType>int</CType>
</RtlPorts>
<RtlPorts>
<name>B_2_q0</name>
<Object>B_2</Object>
<Type>array</Type>
<Scope></Scope>
<IOProtocol>ap_memory</IOProtocol>
<IOConfig></IOConfig>
<Dir>in</Dir>
<Bits>32</Bits>
<Attribute>data</Attribute>
<CType>int</CType>
</RtlPorts>
<RtlPorts>
<name>B_3_address0</name>
<Object>B_3</Object>
<Type>array</Type>
<Scope></Scope>
<IOProtocol>ap_memory</IOProtocol>
<IOConfig></IOConfig>
<Dir>out</Dir>
<Bits>4</Bits>
<Attribute>address</Attribute>
<CType>int</CType>
</RtlPorts>
<RtlPorts>
<name>B_3_ce0</name>
<Object>B_3</Object>
<Type>array</Type>
<Scope></Scope>
<IOProtocol>ap_memory</IOProtocol>
<IOConfig></IOConfig>
<Dir>out</Dir>
<Bits>1</Bits>
<Attribute>control</Attribute>
<CType>int</CType>
</RtlPorts>
<RtlPorts>
<name>B_3_q0</name>
<Object>B_3</Object>
<Type>array</Type>
<Scope></Scope>
<IOProtocol>ap_memory</IOProtocol>
<IOConfig></IOConfig>
<Dir>in</Dir>
<Bits>32</Bits>
<Attribute>data</Attribute>
<CType>int</CType>
</RtlPorts>
<RtlPorts>
<name>C_0_address0</name>
<Object>C_0</Object>
<Type>array</Type>
<Scope></Scope>
<IOProtocol>ap_memory</IOProtocol>
<IOConfig></IOConfig>
<Dir>out</Dir>
<Bits>4</Bits>
<Attribute>address</Attribute>
<CType>int</CType>
</RtlPorts>
<RtlPorts>
<name>C_0_ce0</name>
<Object>C_0</Object>
<Type>array</Type>
<Scope></Scope>
<IOProtocol>ap_memory</IOProtocol>
<IOConfig></IOConfig>
<Dir>out</Dir>
<Bits>1</Bits>
<Attribute>control</Attribute>
<CType>int</CType>
</RtlPorts>
<RtlPorts>
<name>C_0_we0</name>
<Object>C_0</Object>
<Type>array</Type>
<Scope></Scope>
<IOProtocol>ap_memory</IOProtocol>
<IOConfig></IOConfig>
<Dir>out</Dir>
<Bits>1</Bits>
<Attribute>control</Attribute>
<CType>int</CType>
</RtlPorts>
<RtlPorts>
<name>C_0_d0</name>
<Object>C_0</Object>
<Type>array</Type>
<Scope></Scope>
<IOProtocol>ap_memory</IOProtocol>
<IOConfig></IOConfig>
<Dir>out</Dir>
<Bits>32</Bits>
<Attribute>data</Attribute>
<CType>int</CType>
</RtlPorts>
<RtlPorts>
<name>C_1_address0</name>
<Object>C_1</Object>
<Type>array</Type>
<Scope></Scope>
<IOProtocol>ap_memory</IOProtocol>
<IOConfig></IOConfig>
<Dir>out</Dir>
<Bits>4</Bits>
<Attribute>address</Attribute>
<CType>int</CType>
</RtlPorts>
<RtlPorts>
<name>C_1_ce0</name>
<Object>C_1</Object>
<Type>array</Type>
<Scope></Scope>
<IOProtocol>ap_memory</IOProtocol>
<IOConfig></IOConfig>
<Dir>out</Dir>
<Bits>1</Bits>
<Attribute>control</Attribute>
<CType>int</CType>
</RtlPorts>
<RtlPorts>
<name>C_1_we0</name>
<Object>C_1</Object>
<Type>array</Type>
<Scope></Scope>
<IOProtocol>ap_memory</IOProtocol>
<IOConfig></IOConfig>
<Dir>out</Dir>
<Bits>1</Bits>
<Attribute>control</Attribute>
<CType>int</CType>
</RtlPorts>
<RtlPorts>
<name>C_1_d0</name>
<Object>C_1</Object>
<Type>array</Type>
<Scope></Scope>
<IOProtocol>ap_memory</IOProtocol>
<IOConfig></IOConfig>
<Dir>out</Dir>
<Bits>32</Bits>
<Attribute>data</Attribute>
<CType>int</CType>
</RtlPorts>
<RtlPorts>
<name>C_2_address0</name>
<Object>C_2</Object>
<Type>array</Type>
<Scope></Scope>
<IOProtocol>ap_memory</IOProtocol>
<IOConfig></IOConfig>
<Dir>out</Dir>
<Bits>4</Bits>
<Attribute>address</Attribute>
<CType>int</CType>
</RtlPorts>
<RtlPorts>
<name>C_2_ce0</name>
<Object>C_2</Object>
<Type>array</Type>
<Scope></Scope>
<IOProtocol>ap_memory</IOProtocol>
<IOConfig></IOConfig>
<Dir>out</Dir>
<Bits>1</Bits>
<Attribute>control</Attribute>
<CType>int</CType>
</RtlPorts>
<RtlPorts>
<name>C_2_we0</name>
<Object>C_2</Object>
<Type>array</Type>
<Scope></Scope>
<IOProtocol>ap_memory</IOProtocol>
<IOConfig></IOConfig>
<Dir>out</Dir>
<Bits>1</Bits>
<Attribute>control</Attribute>
<CType>int</CType>
</RtlPorts>
<RtlPorts>
<name>C_2_d0</name>
<Object>C_2</Object>
<Type>array</Type>
<Scope></Scope>
<IOProtocol>ap_memory</IOProtocol>
<IOConfig></IOConfig>
<Dir>out</Dir>
<Bits>32</Bits>
<Attribute>data</Attribute>
<CType>int</CType>
</RtlPorts>
<RtlPorts>
<name>C_3_address0</name>
<Object>C_3</Object>
<Type>array</Type>
<Scope></Scope>
<IOProtocol>ap_memory</IOProtocol>
<IOConfig></IOConfig>
<Dir>out</Dir>
<Bits>4</Bits>
<Attribute>address</Attribute>
<CType>int</CType>
</RtlPorts>
<RtlPorts>
<name>C_3_ce0</name>
<Object>C_3</Object>
<Type>array</Type>
<Scope></Scope>
<IOProtocol>ap_memory</IOProtocol>
<IOConfig></IOConfig>
<Dir>out</Dir>
<Bits>1</Bits>
<Attribute>control</Attribute>
<CType>int</CType>
</RtlPorts>
<RtlPorts>
<name>C_3_we0</name>
<Object>C_3</Object>
<Type>array</Type>
<Scope></Scope>
<IOProtocol>ap_memory</IOProtocol>
<IOConfig></IOConfig>
<Dir>out</Dir>
<Bits>1</Bits>
<Attribute>control</Attribute>
<CType>int</CType>
</RtlPorts>
<RtlPorts>
<name>C_3_d0</name>
<Object>C_3</Object>
<Type>array</Type>
<Scope></Scope>
<IOProtocol>ap_memory</IOProtocol>
<IOConfig></IOConfig>
<Dir>out</Dir>
<Bits>32</Bits>
<Attribute>data</Attribute>
<CType>int</CType>
</RtlPorts>
<RtlPorts>
<name>D_0_address0</name>
<Object>D_0</Object>
<Type>array</Type>
<Scope></Scope>
<IOProtocol>ap_memory</IOProtocol>
<IOConfig></IOConfig>
<Dir>out</Dir>
<Bits>4</Bits>
<Attribute>address</Attribute>
<CType>int</CType>
</RtlPorts>
<RtlPorts>
<name>D_0_ce0</name>
<Object>D_0</Object>
<Type>array</Type>
<Scope></Scope>
<IOProtocol>ap_memory</IOProtocol>
<IOConfig></IOConfig>
<Dir>out</Dir>
<Bits>1</Bits>
<Attribute>control</Attribute>
<CType>int</CType>
</RtlPorts>
<RtlPorts>
<name>D_0_we0</name>
<Object>D_0</Object>
<Type>array</Type>
<Scope></Scope>
<IOProtocol>ap_memory</IOProtocol>
<IOConfig></IOConfig>
<Dir>out</Dir>
<Bits>1</Bits>
<Attribute>control</Attribute>
<CType>int</CType>
</RtlPorts>
<RtlPorts>
<name>D_0_d0</name>
<Object>D_0</Object>
<Type>array</Type>
<Scope></Scope>
<IOProtocol>ap_memory</IOProtocol>
<IOConfig></IOConfig>
<Dir>out</Dir>
<Bits>32</Bits>
<Attribute>data</Attribute>
<CType>int</CType>
</RtlPorts>
<RtlPorts>
<name>D_1_address0</name>
<Object>D_1</Object>
<Type>array</Type>
<Scope></Scope>
<IOProtocol>ap_memory</IOProtocol>
<IOConfig></IOConfig>
<Dir>out</Dir>
<Bits>4</Bits>
<Attribute>address</Attribute>
<CType>int</CType>
</RtlPorts>
<RtlPorts>
<name>D_1_ce0</name>
<Object>D_1</Object>
<Type>array</Type>
<Scope></Scope>
<IOProtocol>ap_memory</IOProtocol>
<IOConfig></IOConfig>
<Dir>out</Dir>
<Bits>1</Bits>
<Attribute>control</Attribute>
<CType>int</CType>
</RtlPorts>
<RtlPorts>
<name>D_1_we0</name>
<Object>D_1</Object>
<Type>array</Type>
<Scope></Scope>
<IOProtocol>ap_memory</IOProtocol>
<IOConfig></IOConfig>
<Dir>out</Dir>
<Bits>1</Bits>
<Attribute>control</Attribute>
<CType>int</CType>
</RtlPorts>
<RtlPorts>
<name>D_1_d0</name>
<Object>D_1</Object>
<Type>array</Type>
<Scope></Scope>
<IOProtocol>ap_memory</IOProtocol>
<IOConfig></IOConfig>
<Dir>out</Dir>
<Bits>32</Bits>
<Attribute>data</Attribute>
<CType>int</CType>
</RtlPorts>
<RtlPorts>
<name>D_2_address0</name>
<Object>D_2</Object>
<Type>array</Type>
<Scope></Scope>
<IOProtocol>ap_memory</IOProtocol>
<IOConfig></IOConfig>
<Dir>out</Dir>
<Bits>4</Bits>
<Attribute>address</Attribute>
<CType>int</CType>
</RtlPorts>
<RtlPorts>
<name>D_2_ce0</name>
<Object>D_2</Object>
<Type>array</Type>
<Scope></Scope>
<IOProtocol>ap_memory</IOProtocol>
<IOConfig></IOConfig>
<Dir>out</Dir>
<Bits>1</Bits>
<Attribute>control</Attribute>
<CType>int</CType>
</RtlPorts>
<RtlPorts>
<name>D_2_we0</name>
<Object>D_2</Object>
<Type>array</Type>
<Scope></Scope>
<IOProtocol>ap_memory</IOProtocol>
<IOConfig></IOConfig>
<Dir>out</Dir>
<Bits>1</Bits>
<Attribute>control</Attribute>
<CType>int</CType>
</RtlPorts>
<RtlPorts>
<name>D_2_d0</name>
<Object>D_2</Object>
<Type>array</Type>
<Scope></Scope>
<IOProtocol>ap_memory</IOProtocol>
<IOConfig></IOConfig>
<Dir>out</Dir>
<Bits>32</Bits>
<Attribute>data</Attribute>
<CType>int</CType>
</RtlPorts>
<RtlPorts>
<name>D_3_address0</name>
<Object>D_3</Object>
<Type>array</Type>
<Scope></Scope>
<IOProtocol>ap_memory</IOProtocol>
<IOConfig></IOConfig>
<Dir>out</Dir>
<Bits>4</Bits>
<Attribute>address</Attribute>
<CType>int</CType>
</RtlPorts>
<RtlPorts>
<name>D_3_ce0</name>
<Object>D_3</Object>
<Type>array</Type>
<Scope></Scope>
<IOProtocol>ap_memory</IOProtocol>
<IOConfig></IOConfig>
<Dir>out</Dir>
<Bits>1</Bits>
<Attribute>control</Attribute>
<CType>int</CType>
</RtlPorts>
<RtlPorts>
<name>D_3_we0</name>
<Object>D_3</Object>
<Type>array</Type>
<Scope></Scope>
<IOProtocol>ap_memory</IOProtocol>
<IOConfig></IOConfig>
<Dir>out</Dir>
<Bits>1</Bits>
<Attribute>control</Attribute>
<CType>int</CType>
</RtlPorts>
<RtlPorts>
<name>D_3_d0</name>
<Object>D_3</Object>
<Type>array</Type>
<Scope></Scope>
<IOProtocol>ap_memory</IOProtocol>
<IOConfig></IOConfig>
<Dir>out</Dir>
<Bits>32</Bits>
<Attribute>data</Attribute>
<CType>int</CType>
</RtlPorts>
<RtlPorts>
<name>E_0_address0</name>
<Object>E_0</Object>
<Type>array</Type>
<Scope></Scope>
<IOProtocol>ap_memory</IOProtocol>
<IOConfig></IOConfig>
<Dir>out</Dir>
<Bits>4</Bits>
<Attribute>address</Attribute>
<CType>int</CType>
</RtlPorts>
<RtlPorts>
<name>E_0_ce0</name>
<Object>E_0</Object>
<Type>array</Type>
<Scope></Scope>
<IOProtocol>ap_memory</IOProtocol>
<IOConfig></IOConfig>
<Dir>out</Dir>
<Bits>1</Bits>
<Attribute>control</Attribute>
<CType>int</CType>
</RtlPorts>
<RtlPorts>
<name>E_0_we0</name>
<Object>E_0</Object>
<Type>array</Type>
<Scope></Scope>
<IOProtocol>ap_memory</IOProtocol>
<IOConfig></IOConfig>
<Dir>out</Dir>
<Bits>1</Bits>
<Attribute>control</Attribute>
<CType>int</CType>
</RtlPorts>
<RtlPorts>
<name>E_0_d0</name>
<Object>E_0</Object>
<Type>array</Type>
<Scope></Scope>
<IOProtocol>ap_memory</IOProtocol>
<IOConfig></IOConfig>
<Dir>out</Dir>
<Bits>32</Bits>
<Attribute>data</Attribute>
<CType>int</CType>
</RtlPorts>
<RtlPorts>
<name>E_1_address0</name>
<Object>E_1</Object>
<Type>array</Type>
<Scope></Scope>
<IOProtocol>ap_memory</IOProtocol>
<IOConfig></IOConfig>
<Dir>out</Dir>
<Bits>4</Bits>
<Attribute>address</Attribute>
<CType>int</CType>
</RtlPorts>
<RtlPorts>
<name>E_1_ce0</name>
<Object>E_1</Object>
<Type>array</Type>
<Scope></Scope>
<IOProtocol>ap_memory</IOProtocol>
<IOConfig></IOConfig>
<Dir>out</Dir>
<Bits>1</Bits>
<Attribute>control</Attribute>
<CType>int</CType>
</RtlPorts>
<RtlPorts>
<name>E_1_we0</name>
<Object>E_1</Object>
<Type>array</Type>
<Scope></Scope>
<IOProtocol>ap_memory</IOProtocol>
<IOConfig></IOConfig>
<Dir>out</Dir>
<Bits>1</Bits>
<Attribute>control</Attribute>
<CType>int</CType>
</RtlPorts>
<RtlPorts>
<name>E_1_d0</name>
<Object>E_1</Object>
<Type>array</Type>
<Scope></Scope>
<IOProtocol>ap_memory</IOProtocol>
<IOConfig></IOConfig>
<Dir>out</Dir>
<Bits>32</Bits>
<Attribute>data</Attribute>
<CType>int</CType>
</RtlPorts>
<RtlPorts>
<name>E_2_address0</name>
<Object>E_2</Object>
<Type>array</Type>
<Scope></Scope>
<IOProtocol>ap_memory</IOProtocol>
<IOConfig></IOConfig>
<Dir>out</Dir>
<Bits>4</Bits>
<Attribute>address</Attribute>
<CType>int</CType>
</RtlPorts>
<RtlPorts>
<name>E_2_ce0</name>
<Object>E_2</Object>
<Type>array</Type>
<Scope></Scope>
<IOProtocol>ap_memory</IOProtocol>
<IOConfig></IOConfig>
<Dir>out</Dir>
<Bits>1</Bits>
<Attribute>control</Attribute>
<CType>int</CType>
</RtlPorts>
<RtlPorts>
<name>E_2_we0</name>
<Object>E_2</Object>
<Type>array</Type>
<Scope></Scope>
<IOProtocol>ap_memory</IOProtocol>
<IOConfig></IOConfig>
<Dir>out</Dir>
<Bits>1</Bits>
<Attribute>control</Attribute>
<CType>int</CType>
</RtlPorts>
<RtlPorts>
<name>E_2_d0</name>
<Object>E_2</Object>
<Type>array</Type>
<Scope></Scope>
<IOProtocol>ap_memory</IOProtocol>
<IOConfig></IOConfig>
<Dir>out</Dir>
<Bits>32</Bits>
<Attribute>data</Attribute>
<CType>int</CType>
</RtlPorts>
<RtlPorts>
<name>E_3_address0</name>
<Object>E_3</Object>
<Type>array</Type>
<Scope></Scope>
<IOProtocol>ap_memory</IOProtocol>
<IOConfig></IOConfig>
<Dir>out</Dir>
<Bits>4</Bits>
<Attribute>address</Attribute>
<CType>int</CType>
</RtlPorts>
<RtlPorts>
<name>E_3_ce0</name>
<Object>E_3</Object>
<Type>array</Type>
<Scope></Scope>
<IOProtocol>ap_memory</IOProtocol>
<IOConfig></IOConfig>
<Dir>out</Dir>
<Bits>1</Bits>
<Attribute>control</Attribute>
<CType>int</CType>
</RtlPorts>
<RtlPorts>
<name>E_3_we0</name>
<Object>E_3</Object>
<Type>array</Type>
<Scope></Scope>
<IOProtocol>ap_memory</IOProtocol>
<IOConfig></IOConfig>
<Dir>out</Dir>
<Bits>1</Bits>
<Attribute>control</Attribute>
<CType>int</CType>
</RtlPorts>
<RtlPorts>
<name>E_3_d0</name>
<Object>E_3</Object>
<Type>array</Type>
<Scope></Scope>
<IOProtocol>ap_memory</IOProtocol>
<IOConfig></IOConfig>
<Dir>out</Dir>
<Bits>32</Bits>
<Attribute>data</Attribute>
<CType>int</CType>
</RtlPorts>
</InterfaceSummary>
</Module>
</ModuleInformation>

<FIFOInformation>
</FIFOInformation>

</profile>
